lib/__init__.py
lib/bmi.py
lib/functions.py
lib/hello.py
lib/testClass.py
PKLtestPackk-0.0.7.dist-info/METADATA
PKLtestPackk-0.0.7.dist-info/WHEEL
PKLtestPackk-0.0.7.dist-info/top_level.txt
PKLtestPackk-0.0.7.dist-info/RECORD
