Metadata-Version: 2.1
Name: PKLtestPackk
Version: 0.0.7
Summary: A base hello world package
Author: Pradeep KL
Author-email: <pradeep.karmaalab@gmail.com>
License: UNKNOWN
Keywords: python,video,stream,video stream,camera stream,sockets
Platform: UNKNOWN
Classifier: Development Status :: 1 - Planning
Classifier: Intended Audience :: Developers
Classifier: Programming Language :: Python :: 3
Classifier: Operating System :: Unix
Classifier: Operating System :: MacOS :: MacOS X
Classifier: Operating System :: Microsoft :: Windows
